pymodaq_plugins_montana/__init__.py
pymodaq_plugins_montana/utils.py
pymodaq_plugins_montana/app/__init__.py
pymodaq_plugins_montana/app/custom_app_template.py
pymodaq_plugins_montana/daq_move_plugins/__init__.py
pymodaq_plugins_montana/daq_move_plugins/daq_move_CryoTemperature.py
pymodaq_plugins_montana/daq_move_plugins/daq_move_Rook.py
pymodaq_plugins_montana/daq_viewer_plugins/__init__.py
pymodaq_plugins_montana/daq_viewer_plugins/plugins_0D/__init__.py
pymodaq_plugins_montana/daq_viewer_plugins/plugins_0D/daq_0Dviewer_CryoInfo.py
pymodaq_plugins_montana/daq_viewer_plugins/plugins_1D/__init__.py
pymodaq_plugins_montana/daq_viewer_plugins/plugins_2D/__init__.py
pymodaq_plugins_montana/daq_viewer_plugins/plugins_ND/__init__.py
pymodaq_plugins_montana/exporters/__init__.py
pymodaq_plugins_montana/extensions/__init__.py
pymodaq_plugins_montana/extensions/custom_extension_template.py
pymodaq_plugins_montana/hardware/TcPlot.py
pymodaq_plugins_montana/hardware/__init__.py
pymodaq_plugins_montana/hardware/cryocore.py
pymodaq_plugins_montana/hardware/fsr.py
pymodaq_plugins_montana/hardware/genericcryostat.py
pymodaq_plugins_montana/hardware/gui_helpers.py
pymodaq_plugins_montana/hardware/instrument.py
pymodaq_plugins_montana/hardware/mirs_helpers.py
pymodaq_plugins_montana/hardware/pegasus.py
pymodaq_plugins_montana/hardware/rook.py
pymodaq_plugins_montana/hardware/scryostation.py
pymodaq_plugins_montana/hardware/ssh_tunnel.py
pymodaq_plugins_montana/hardware/xpcryostation.py
pymodaq_plugins_montana/models/PIDModelTemplate.py
pymodaq_plugins_montana/models/__init__.py
pymodaq_plugins_montana/resources/__init__.py
pymodaq_plugins_montana/resources/config_template.toml
pymodaq_plugins_montana/scanners/__init__.py
pymodaq_plugins_montana-0.0.2.dist-info/METADATA
pymodaq_plugins_montana-0.0.2.dist-info/WHEEL
pymodaq_plugins_montana-0.0.2.dist-info/entry_points.txt
pymodaq_plugins_montana-0.0.2.dist-info/licenses/LICENSE
pymodaq_plugins_montana-0.0.2.dist-info/RECORD
